sc8pr/__init__.py
sc8pr/_cs.py
sc8pr/_event.py
sc8pr/geom.py
sc8pr/sc8pr.data
sc8pr/sprite.py
sc8pr/text.py
sc8pr/util.py
sc8pr/effect/__init__.py
sc8pr/effect/math.py
sc8pr/effect/stamp.py
sc8pr/gui/__init__.py
sc8pr/gui/button.py
sc8pr/gui/dialog.py
sc8pr/gui/menu.py
sc8pr/gui/radio.py
sc8pr/gui/scroll.py
sc8pr/gui/slider.py
sc8pr/gui/tbcanvas.py
sc8pr/gui/textinput.py
sc8pr/gui/tk.py
sc8pr/misc/__init__.py
sc8pr/misc/cursors.py
sc8pr/misc/effect.py
sc8pr/misc/hsv.py
sc8pr/misc/progress.py
sc8pr/misc/table.py
sc8pr/misc/typeset.py
sc8pr/misc/video.py
sc8pr/plot/__init__.py
sc8pr/plot/json.py
sc8pr/plot/regression.py
sc8pr/robot/__init__.py
sc8pr/robot/arena.py
sc8pr/robot/gui.py
sc8pr/robot/park.py
sc8pr/robot/party.py
sc8pr/robot/soccer.py
sc8pr/shape/__init__.py
sc8pr/shape/locus.py
sc8pr-3.0.4.dist-info/LICENSE.txt
sc8pr-3.0.4.dist-info/METADATA
sc8pr-3.0.4.dist-info/WHEEL
sc8pr-3.0.4.dist-info/top_level.txt
sc8pr-3.0.4.dist-info/RECORD
