Metadata-Version: 2.1
Name: sc8pr
Version: 3.0.4
Summary: A simple framework for new and experienced Python programmers to create animations, games, robotics simulations, and other graphics-based programs
Home-page: https://dmaccarthy.github.io/sc8pr
Author: D.G. MacCarthy
Author-email: sc8pr.py@gmail.com
License: GPLv3
Keywords: graphics animation sprite gui robotics pygame educational
Classifier: Development Status :: 5 - Production/Stable
Classifier: Intended Audience :: Developers
Classifier: Intended Audience :: Education
Classifier: License :: OSI Approved :: GNU General Public License v3 (GPLv3)
Classifier: Programming Language :: Python :: 3
Classifier: Topic :: Software Development :: Libraries :: pygame
Classifier: Topic :: Multimedia :: Graphics
Classifier: Topic :: Education
Classifier: Topic :: Games/Entertainment
Requires-Python: >=3.7
License-File: LICENSE.txt
Requires-Dist: pygame <3,>=1.9.2
